{
  "templates": [
    {
      "id": "cloudflare-app-builder",
      "type": "agent",
      "name": "Cloudflare App Builder",
      "version": "0.3.0",
      "description": "An agent that builds full-stack web apps on Cloudflare Workers — React + Vite SPA with a Worker API backend — and ships every project to GitHub. It builds; it does not deploy.",
      "hash": "0371984da5d7637fff2f7e0ca594c8e2ff0120d9"
    },
    {
      "id": "cloudflare-deployment-engineer",
      "type": "agent",
      "name": "Cloudflare Deployment Engineer",
      "version": "0.2.0",
      "description": "An agent that deploys any Cloudflare Workers app straight from its GitHub repo, using the terminal — gh + wrangler with sandbox-exposed credentials, no bespoke tools.",
      "hash": "f936fbb16a0f841c0c8b8e96f6293351a2300778"
    },
    {
      "id": "writing-a-prd",
      "type": "skill",
      "name": "Writing a PRD",
      "version": "0.1.0",
      "description": "A playbook for writing product requirements documents that lead with the decision.",
      "hash": "e8e83497f157254486e5ba391d58d81d4bbb6069"
    },
    {
      "id": "cloudflare-deploy",
      "type": "tool",
      "name": "Cloudflare Deploy",
      "version": "0.1.0",
      "description": "Deploy a Cloudflare Worker with wrangler, using credentials from the environment.",
      "hash": "7a15a4679f4596af384b69e43d2aebc868de7b7e"
    }
  ]
}
